{
  "hash": "20d08183a3ec24a847aa976a7675f100",
  "result": {
    "markdown": "---\ntitle: \"Segmenting for Perspective\"\ndescription: \"Discover Insight through Segmentation\"\nauthor: \"Cozmina Secula\"\ndate: \"2023-10-29\"\ncategories: [employee segmentation, peope analytics]\n\n---\n\n\n# Introduction\n\nSegmentation is an essential part of any analytics, helping to understand and derive insights from data.\n\nIn this project, I use segmentation to understand compensation differences across various factors such as roles, departments, experience, and demographic groups through segmented employee data. This may help inform the development of a competitive compensation strategy.\nA competitive compensation strategy can help attract and retain top talent, improve employee morale and motivation, and ultimately drive business success.\n\n# Slides\n\n\n::: {.cell}\n::: {.cell-output-display}\n```{=html}\n<div class=\"shareagain\" style=\"min-width:300px;margin:0 auto;\" data-exeternal=\"1\">\n<iframe src=\"./2023-10-29-segmenting-for-perspective/01-slides-x.html\" width=\"1600\" height=\"900\" style=\"border:none;\" loading=\"lazy\" allowfullscreen></iframe>\n<script>fitvids('.shareagain', {players: 'iframe'});</script>\n</div>\n```\n:::\n:::\n",
    "supporting": [],
    "filters": [
      "rmarkdown/pagebreak.lua"
    ],
    "includes": {
      "include-in-header": [
        "<script src=\"../../site_libs/fitvids-2.1.1/fitvids.min.js\"></script>\r\n"
      ]
    },
    "engineDependencies": {},
    "preserve": {},
    "postProcess": true
  }
}